DBDoc-0.0.1.data/data/style.css
dbdoc/__init__.py
dbdoc/cli.py
dbdoc/style.css
DBDoc-0.0.1.dist-info/LICENSE
DBDoc-0.0.1.dist-info/METADATA
DBDoc-0.0.1.dist-info/WHEEL
DBDoc-0.0.1.dist-info/entry_points.txt
DBDoc-0.0.1.dist-info/top_level.txt
DBDoc-0.0.1.dist-info/RECORD
