Metadata-Version: 2.1
Name: DBDoc
Version: 0.0.1
Summary: A simple database doc with one html file
Home-page: https://github.com/faeli/dbdoc
Author: Feng pengbin
Author-email: fengpengbin@live.cn
Maintainer: Feng pengbin
Maintainer-email: fengpengbin@live.cn
License: Apache License 2.0
Project-URL: Documentation, https://github.com/faeli/dbdoc/wiki
Project-URL: Code, https://github.com/faeli/dbdoc
Project-URL: Issue tracker, https://github.com/faeli/dbdoc/issues
Platform: any
Requires-Python: >=2.7,!=3.0.*,!=3.1.*,!=3.2.*,!=3.3.*
Requires-Dist: SQLAlchemy (>=1.2)
